robin_stocks/__init__.py
robin_stocks/account.py
robin_stocks/authentication.py
robin_stocks/crypto.py
robin_stocks/export.py
robin_stocks/globals.py
robin_stocks/helper.py
robin_stocks/markets.py
robin_stocks/options.py
robin_stocks/orders.py
robin_stocks/profiles.py
robin_stocks/stocks.py
robin_stocks/urls.py
collegroup_robinstocks-1.0.0.dist-info/LICENSE.txt
collegroup_robinstocks-1.0.0.dist-info/METADATA
collegroup_robinstocks-1.0.0.dist-info/WHEEL
collegroup_robinstocks-1.0.0.dist-info/top_level.txt
collegroup_robinstocks-1.0.0.dist-info/RECORD
