Metadata-Version: 2.1
Name: collegroup-robinstocks
Version: 1.0.0
Summary: A Python wrapper around the Robinhood API
Home-page: https://github.com/collegroup/robin_stocks
Author: Colle Group
Author-email: arthur@collegroup.com
License: MIT
Keywords: robinhood,robin stocks,finance app,stocks,options,trading,investing
Platform: UNKNOWN
Requires: requests
Requires-Python: >=3
Requires-Dist: requests
